udm.cp39-win32.pyd
Udm-3.2.3.dist-info/METADATA
Udm-3.2.3.dist-info/WHEEL
Udm-3.2.3.dist-info/top_level.txt
Udm-3.2.3.dist-info/RECORD
