Metadata-Version: 2.1
Name: Udm
Version: 3.2.3
Summary: Universal Data Model
Home-page: http://repo.isis.vanderbilt.edu/
Author: Kevin Smyth
Author-email: ksmyth@isis.vanderbilt.edu
License: Vanderbilt UDM License
Platform: UNKNOWN
